cylimiter.cpython-310-darwin.so
extensions/__init__.py
cylimiter-0.4.2.dist-info/LICENSE
cylimiter-0.4.2.dist-info/METADATA
cylimiter-0.4.2.dist-info/WHEEL
cylimiter-0.4.2.dist-info/top_level.txt
cylimiter-0.4.2.dist-info/RECORD
